pygbop/__init__.py
pygbop/common.py
pygbop/event_push.py
pygbop/gbop.py
pygbop-0.2.7.53.dist-info/METADATA
pygbop-0.2.7.53.dist-info/WHEEL
pygbop-0.2.7.53.dist-info/top_level.txt
pygbop-0.2.7.53.dist-info/RECORD
